LICENSE
marco_test_package/__init__.py
marco_test_package/marco_test_package.py
marco_test_package/py.typed
marco_test_package-0.1.0.dist-info/LICENSE
marco_test_package-0.1.0.dist-info/WHEEL
marco_test_package-0.1.0.dist-info/METADATA
marco_test_package-0.1.0.dist-info/RECORD
