Metadata-Version: 2.1
Name: marco-test-package
Version: 0.1.0
Summary: Test package for marco
Home-page: https://github.com/mgancita/marco-test-package
License: MIT
Author: Marco Gancitano
Author-email: marco.gancitano@example.com
Requires-Python: >=3.7,<4.0
Classifier: License :: OSI Approved :: MIT License
Classifier: Natural Language :: English
Classifier: Programming Language :: Python :: 3
Classifier: Programming Language :: Python :: 3.7
Classifier: Programming Language :: Python :: 3.8
Classifier: Programming Language :: Python :: 3.9
